MANIFEST.in
README.rst
setup.cfg
setup.py
tox.ini
django_geoip_redis.egg-info/PKG-INFO
django_geoip_redis.egg-info/SOURCES.txt
django_geoip_redis.egg-info/dependency_links.txt
django_geoip_redis.egg-info/not-zip-safe
django_geoip_redis.egg-info/requires.txt
django_geoip_redis.egg-info/top_level.txt
docs/__init__.py
docs/conf.py
geoip/__init__.py
geoip/admin.py
geoip/defaults.py
geoip/geo.py
geoip/middleware.py
geoip/models.py
geoip/provider.py
geoip/redis_wrapper.py
geoip/tasks.py
geoip/test_cases.py
geoip/test_settings.py
geoip/urls.py
geoip/views.py
geoip/locale/ru/LC_MESSAGES/django.po
geoip/management/__init__.py
geoip/management/commands/__init__.py
geoip/management/commands/sync_with_redis.py
geoip/management/commands/update_geo_db.py
geoip/migrations/0001_initial.py
geoip/migrations/__init__.py
geoip/templates/geoip/range.html
geoip/templates/geoip/admin/change_list_link.html
geoip/templates/geoip/admin/sync.html
requirements/package.txt
requirements/readthedocs.txt
requirements/tests.txt