Metadata-Version: 1.1
Name: django-geoip-redis
Version: 1.2.2
Summary: Django GeoIP. Based on default DB or Redis.
Home-page: https://github.com/gotlium/django-geoip-redis
Author: GoTLiuM InSPiRiT
Author-email: gotlium@gmail.com
License: GPL v3
Keywords: django geoip mysql redis
Platform: UNKNOWN
Classifier: Development Status :: 5 - Production/Stable
Classifier: Environment :: Console
Classifier: Environment :: Web Environment
Classifier: Framework :: Django
Classifier: Intended Audience :: Developers
Classifier: Intended Audience :: System Administrators
Classifier: License :: OSI Approved :: GNU General Public License v3 (GPLv3)
Classifier: Operating System :: OS Independent
Classifier: Programming Language :: Python
Classifier: Programming Language :: Python :: 2.6
Classifier: Programming Language :: Python :: 2.7
Classifier: Programming Language :: Python :: 3.3
